R07.py
R07-0.0.3.1.dist-info/LICENSE.md
R07-0.0.3.1.dist-info/METADATA
R07-0.0.3.1.dist-info/WHEEL
R07-0.0.3.1.dist-info/top_level.txt
R07-0.0.3.1.dist-info/RECORD
