Metadata-Version: 2.1
Name: R07
Version: 0.0.3.1
Summary: Utlity Packages Developed by R-07!
Home-page: https://github.com/rahulbordoloi/PyPI-Publish
Author: Rahul Bordoloi
Author-email: mail@rahulbordoloi.me
Classifier: Programming Language :: Python :: 3
Classifier: Programming Language :: Python :: 3.6
Classifier: Programming Language :: Python :: 3.7
Classifier: Programming Language :: Python :: 3.8
Classifier: Operating System :: OS Independent
Classifier: License :: OSI Approved :: MIT License
Classifier: Topic :: Utilities
Classifier: Natural Language :: English
Classifier: Development Status :: 5 - Production/Stable
License-File: LICENSE.md
Requires-Dist: blessings ~=1.7
Requires-Dist: pytube3 ~=9.6.4
Provides-Extra: dev
Requires-Dist: pytest >=3.7 ; extra == 'dev'
